{"__symbolic":"module","version":4,"metadata":{"CoreModule":{"__symbolic":"class","decorators":[{"__symbolic":"call","expression":{"__symbolic":"reference","module":"@angular/core","name":"NgModule","line":20,"character":1},"arguments":[{"declarations":[{"__symbolic":"reference","name":"TranslatePipe"},{"__symbolic":"reference","name":"CamelCasePipe"},{"__symbolic":"reference","name":"NoValuePipe"},{"__symbolic":"reference","name":"NavbarComponent"},{"__symbolic":"reference","name":"SidenavComponent"},{"__symbolic":"reference","name":"ResponsiveNavbarComponent"},{"__symbolic":"reference","name":"ProgramSidenavComponent"}],"imports":[{"__symbolic":"reference","module":"ngx-spinner","name":"NgxSpinnerModule","line":31,"character":4},{"__symbolic":"reference","module":"@angular/common","name":"CommonModule","line":32,"character":4},{"__symbolic":"reference","module":"@angular/router","name":"RouterModule","line":33,"character":4},{"__symbolic":"reference","module":"@angular/common/http","name":"HttpClientModule","line":34,"character":4},{"__symbolic":"reference","module":"@angular/material","name":"MatButtonModule","line":35,"character":4},{"__symbolic":"reference","module":"@angular/material","name":"MatMenuModule","line":36,"character":4},{"__symbolic":"reference","module":"@angular/material","name":"MatIconModule","line":37,"character":4},{"__symbolic":"reference","module":"@angular/http","name":"HttpModule","line":38,"character":4},{"__symbolic":"reference","module":"@angular/material","name":"MatCardModule","line":39,"character":4},{"__symbolic":"reference","module":"@angular/common/http","name":"HttpClientModule","line":40,"character":4},{"__symbolic":"reference","module":"@angular/material","name":"MatDividerModule","line":41,"character":4},{"__symbolic":"reference","module":"@angular/material","name":"MatTooltipModule","line":42,"character":4}],"providers":[{"provide":{"__symbolic":"reference","module":"@angular/common/http","name":"HTTP_INTERCEPTORS","line":46,"character":15},"useClass":{"__symbolic":"reference","name":"ApiInterceptor"},"multi":true}],"exports":[{"__symbolic":"reference","name":"TranslatePipe"},{"__symbolic":"reference","name":"NavbarComponent"},{"__symbolic":"reference","name":"SidenavComponent"},{"__symbolic":"reference","name":"ResponsiveNavbarComponent"},{"__symbolic":"reference","name":"CamelCasePipe"},{"__symbolic":"reference","name":"NoValuePipe"},{"__symbolic":"reference","name":"ProgramSidenavComponent"},{"__symbolic":"reference","module":"@angular/common","name":"CommonModule","line":59,"character":4}]}]}],"members":{},"statics":{"forRoot":{"__symbolic":"function","parameters":[],"value":{"ngModule":{"__symbolic":"reference","name":"CoreModule"},"providers":[{"__symbolic":"reference","name":"TranslateService"},{"__symbolic":"reference","name":"UtilityService"},{"__symbolic":"reference","name":"ApiInterceptor"},{"__symbolic":"reference","name":"ApiService"}]}}}},"CamelCasePipe":{"__symbolic":"class","decorators":[{"__symbolic":"call","expression":{"__symbolic":"reference","module":"@angular/core","name":"Pipe","line":2,"character":1},"arguments":[{"name":"camelcase","pure":false}]}],"members":{"__ctor__":[{"__symbolic":"constructor"}],"transform":[{"__symbolic":"method"}]}},"NoValuePipe":{"__symbolic":"class","decorators":[{"__symbolic":"call","expression":{"__symbolic":"reference","module":"@angular/core","name":"Pipe","line":2,"character":1},"arguments":[{"name":"blank","pure":false}]}],"members":{"__ctor__":[{"__symbolic":"constructor"}],"transform":[{"__symbolic":"method"}]}},"TranslatePipe":{"__symbolic":"class","decorators":[{"__symbolic":"call","expression":{"__symbolic":"reference","module":"@angular/core","name":"Pipe","line":3,"character":1},"arguments":[{"name":"translate","pure":false}]}],"members":{"__ctor__":[{"__symbolic":"constructor","parameters":[{"__symbolic":"reference","name":"TranslateService"}]}],"transform":[{"__symbolic":"method"}]}},"ApiService":{"__symbolic":"class","decorators":[{"__symbolic":"call","expression":{"__symbolic":"reference","module":"@angular/core","name":"Injectable","line":3,"character":1},"arguments":[{"providedIn":"root"}]}],"members":{"__ctor__":[{"__symbolic":"constructor","parameters":[{"__symbolic":"reference","module":"@angular/common/http","name":"HttpClient","line":8,"character":28}]}],"get":[{"__symbolic":"method"}],"getJSON":[{"__symbolic":"method"}],"post":[{"__symbolic":"method"}],"upload":[{"__symbolic":"method"}]},"statics":{"ngInjectableDef":{}}},"ApiInterceptor":{"__symbolic":"class","decorators":[{"__symbolic":"call","expression":{"__symbolic":"reference","module":"@angular/core","name":"Injectable","line":8,"character":1}}],"members":{"intercept":[{"__symbolic":"method"}]}},"TranslateService":{"__symbolic":"class","decorators":[{"__symbolic":"call","expression":{"__symbolic":"reference","module":"@angular/core","name":"Injectable","line":3,"character":1}}],"members":{"__ctor__":[{"__symbolic":"constructor","parameters":[{"__symbolic":"reference","module":"@angular/common/http","name":"HttpClient","line":8,"character":28}]}],"use":[{"__symbolic":"method"}]}},"UtilityService":{"__symbolic":"class","decorators":[{"__symbolic":"call","expression":{"__symbolic":"reference","module":"@angular/core","name":"Injectable","line":4,"character":1},"arguments":[{"providedIn":"root"}]}],"members":{"__ctor__":[{"__symbolic":"constructor","parameters":[{"__symbolic":"reference","module":"@angular/common","name":"Location","line":8,"character":32},{"__symbolic":"reference","module":"ngx-spinner","name":"NgxSpinnerService","line":8,"character":58}]}],"onBack":[{"__symbolic":"method"}],"loaderShow":[{"__symbolic":"method"}],"loaderHide":[{"__symbolic":"method"}],"toGroup":[{"__symbolic":"method"}],"createFormArray":[{"__symbolic":"method"}]},"statics":{"ngInjectableDef":{}}},"NavbarComponent":{"__symbolic":"class","decorators":[{"__symbolic":"call","expression":{"__symbolic":"reference","module":"@angular/core","name":"Component","line":2,"character":1},"arguments":[{"selector":"app-navbar","template":"<div *ngIf=\"currentUser\">\n\n<nav class=\"navbar noMarginPadding \">\n\n    <div class=\"col-sm-6  col-md-6 col-xs-6 col-lg-6 alingCenterline noMarginPadding\">\n  \n      <img  class=\"logo\" src ={{logo}} >\n      <!-- <mat-card-title class=\"pageBrand\">\n        <strong>{{ 'brand' | translate }}</strong>\n      </mat-card-title> -->\n        </div>\n  \n    <!-- <div class=\"col-sm-4 mod \">\n         <mat-card-title style=\"font-size:18px; color:gray; text-align: center;\" >\n          Sikhshalocham Samikhsa \n            <mat-icon svgIcon=\"thumbs-up\" style=\"font-size:29px; color: gray;\">\n            </mat-icon>\n        </mat-card-title> \n      </div> -->\n  \n    <div class=\"col-sm-6 col-md-6 col-xs-6 col-lg-6 \">\n      <span class=\"right _flex-box alingCenterline\">\n        <button mat-icon-button (click)=\"openDropdown()\">\n              <i class=\"material-icons\">\n                  apps\n                  </i>\n        </button>\n            <div id=\"overlay\" (click)=\"openDropdown()\" *ngIf=\"showDropdown\">\n              <div class=\"dropdownDiv\">\n                <div class=\"col-sm-3 dropdownFeature\">\n                    <div class=\"verticalCenteralign\">\n                      <div class=\"apple\" >\n                        <i class=\"material-icons\" id=\"whiteIcon\">\n                          create\n                        </i>\n                      </div>\n                      <div class=\"active\">\n                        {{'menuDropdown.myApps' | translate}}\n                      </div>\n                    </div>\n                </div>\n              </div>\n            </div>\n      <span mat-button [matMenuTriggerFor]=\"menu\" class=\"alingCenterline _cursor-pointer\">\n              <i class=\"material-icons brand dropdownIcon\">\n                  person\n                  </i>\n            <!-- <span class=\"brand \">{{currentUser?.name}}</span> -->\n        <i class=\"material-icons brand icon\">\n          keyboard_arrow_down\n        </i>\n      </span>\n      <mat-menu #menu=\"matMenu\">\n        <span mat-menu-item class=\"matmenuIcon\">\n            <i class=\"material-icons\">\n                supervised_user_circle\n            </i>\n            <span class=\"padding\">{{currentUser?.email}}</span>\n        </span>\n        <mat-divider></mat-divider>\n        <span mat-menu-item  class=\"matmenuIcon black\">\n          <i class=\"material-icons\">\n            done\n          </i>\n          <span class=\"padding\">{{currentUser?.name}}</span>\n        </span>\n        <mat-divider></mat-divider>\n        <span mat-menu-item class=\"padding\" (click)=\"onSignout()\">\n          <span class=\"bigPadding black\">\n              {{'menuDropdown.signOut' | translate}}\n          </span>\n        </span>\n      </mat-menu>\n      <!-- <div class=\"right horizontalLine\">\n        <i class=\"material-icons brand helpIcon\">\n          help_outline\n        </i>\n      </div> -->\n  </span>\n  \n    </div>\n  </nav>\n</div>","styles":[".noMarginPadding{margin:0;padding:0}.brand{color:var(--primary-color);margin-bottom:0}.logo{height:50px}.apple{background-image:linear-gradient(to bottom,#1cdffe 10%,#2462e9 90%);height:80px;width:80px;border:1px solid var(--primary-color);border-radius:15px;padding:10px;display:flex;align-items:center;justify-content:center}.horizontalLine{position:relative;padding:0 8px}.icon{font-size:16px;padding-right:10px}.helpIcon{font-weight:10px}.horizontalLine:before{content:\"\";background:var(--border-color);position:absolute;bottom:20%;left:-5px;height:60%;width:1px}.navbar{display:flex;align-items:center}.line{line-height:12px}.navicon{font-size:80px;color:linear-gradient(to bottom,from var(--primary-color) 100%,to var(--blue-gradient) 100%)}.dropdownDiv{color:#000;background-color:#fff;position:absolute;min-width:500px;height:350px;right:8px;top:35px;z-index:105;border-radius:2px;box-shadow:0 0 3px 3px rgba(0,0,0,.08);margin:20px;padding:20px 0}.dropdownDiv:before{content:\"\";position:absolute;top:-27px;right:60px;border-left:13px solid transparent;border-right:13px solid transparent;border-top:13px solid transparent;border-bottom:13px solid rgba(0,0,0,.08)}.dropdownDiv:after{content:\"\";position:absolute;top:-24px;right:60px;border-left:12px solid transparent;border-right:12px solid transparent;border-top:12px solid transparent;border-bottom:12px solid #fff}.dropdownFeature{padding:20px}#overlay{position:fixed;display:hidden;width:100%;height:100%;top:0;left:0;right:0;bottom:0;background-color:transperent;z-index:101}#whiteIcon{color:#fff;font-size:45px;line-height:1}.verticalCenteralign{display:flex;flex-direction:column;align-items:center;cursor:pointer}.pageBrand{font-size:18px;padding:0 10px;margin-bottom:0}.pageMenu{margin-bottom:0}.alingCenterline{display:flex;align-items:center}.dropdownIcon{top:1px;line-height:2}.active{margin-top:10px;border-radius:12px;border:1px solid #46a9ff;padding:5px 10px;background-color:#e5f2fe;width:-webkit-fit-content;width:-moz-fit-content;width:fit-content;white-space:nowrap;font-size:11px}.right{display:flex;justify-content:flex-end}.matmenuIcon{display:flex;align-items:center;color:#bababa}.padding{padding-left:10px}.bigPadding{padding-left:40px}.black{color:#4c4c4c}"]}]}],"members":{"dropdownLabel":[{"__symbolic":"property","decorators":[{"__symbolic":"call","expression":{"__symbolic":"reference","module":"@angular/core","name":"Input","line":9,"character":3}}]}],"currentUser":[{"__symbolic":"property","decorators":[{"__symbolic":"call","expression":{"__symbolic":"reference","module":"@angular/core","name":"Input","line":10,"character":3}}]}],"logo":[{"__symbolic":"property","decorators":[{"__symbolic":"call","expression":{"__symbolic":"reference","module":"@angular/core","name":"Input","line":11,"character":3}}]}],"Logout":[{"__symbolic":"property","decorators":[{"__symbolic":"call","expression":{"__symbolic":"reference","module":"@angular/core","name":"Output","line":12,"character":3}}]}],"__ctor__":[{"__symbolic":"constructor"}],"ngOnInit":[{"__symbolic":"method"}],"openDropdown":[{"__symbolic":"method"}],"onSignout":[{"__symbolic":"method"}]}},"ProgramSidenavComponent":{"__symbolic":"class","decorators":[{"__symbolic":"call","expression":{"__symbolic":"reference","module":"@angular/core","name":"Component","line":2,"character":1},"arguments":[{"selector":"app-program-sidenav","template":"<div class=\"heading\">\n    {{ 'headings.programs' | translate }}\n</div>\n<div class=\"subHeading\" *ngFor=\"let results of result; let i=index\" (click)=\"programSelect(results, i)\">\n    <span class=\"sideNavSubheading\" [ngClass]=\"{'active': currentProgramIndex === i}\">\n        <div class=\"overFlowHidden\" matTooltip=\"{{results.name}}\" >\n            {{results.name}}\n        </div>\n    </span>\n</div>\n","styles":[".sideNavSubheading{font-size:15px;padding:10px 23px;min-height:40px;display:flex;cursor:pointer;white-space:nowrap;overflow:hidden;text-overflow:ellipsis}.subHeading{color:var(--grey-color)}.active,.subHeading:hover{color:var(--white-color);background-color:var(--primary-color)}.heading{height:40px;display:flex;align-items:center;padding:0 0 0 15px}.overFlowHidden{white-space:nowrap;text-overflow:ellipsis;overflow:hidden}"]}]}],"members":{"result":[{"__symbolic":"property","decorators":[{"__symbolic":"call","expression":{"__symbolic":"reference","module":"@angular/core","name":"Input","line":8,"character":3}}]}],"__ctor__":[{"__symbolic":"constructor"}],"program":[{"__symbolic":"property","decorators":[{"__symbolic":"call","expression":{"__symbolic":"reference","module":"@angular/core","name":"Output","line":13,"character":3}}]}],"ngOnInit":[{"__symbolic":"method"}],"programSelect":[{"__symbolic":"method"}]}},"ResponsiveNavbarComponent":{"__symbolic":"class","decorators":[{"__symbolic":"call","expression":{"__symbolic":"reference","module":"@angular/core","name":"Component","line":2,"character":1},"arguments":[{"selector":"app-responsive-navbar","template":"<nav class=\"responsiveNavbar noMarginPadding\">\n  <body class=\" col-xs-12 noMarginPadding alingCenterline\" >\n      <span class=\"col-xs-4 alingCenterline noMarginPadding\">\n          <button mat-icon-button>\n          <i class=\"material-icons\" (click)=\"openSideNav()\">\n            menu\n              </i>\n              </button>\n      </span>\n    \n    <mat-card-title class=\"pageBrand col-xs-4 alingCenterline\">\n        <img  class=\"logo\" src ={{logo}} >\n      <!-- <strong>{{ 'brandResponsive' | translate }}</strong> -->\n    </mat-card-title>\n\n    <span class=\"col-xs-4 noMarginPadding _flexEnd\">\n        <button mat-icon-button [matMenuTriggerFor]=\"menu\" class=\" _cursor-pointer\">\n          <i class=\"material-icons dropdownIcon\">\n              person\n              </i>\n        </button>\n        <mat-menu #menu=\"matMenu\">\n          <span mat-menu-item class=\"matmenuIcon\">\n            <i class=\"material-icons\">\n              supervised_user_circle\n            </i>\n            <span class=\"padding\">{{currentUser?.email}}</span>\n          </span>\n          <mat-divider></mat-divider>\n          <span mat-menu-item class=\"matmenuIcon black\">\n            <i class=\"material-icons\">\n              done\n            </i>\n            <span class=\"padding\">{{currentUser?.name}}</span>\n          </span>\n          <mat-divider></mat-divider>\n          <span mat-menu-item class=\"padding\" (click)=\"onSignout()\">\n            <span class=\"bigPadding \">\n              {{'menuDropdown.signOut' | translate}}\n            </span>\n          </span>\n  \n        </mat-menu>\n      </span>\n    \n    </body>\n</nav>","styles":[".noMarginPadding{margin:0;padding:0}.icon{font-size:16px;padding-right:10px}._flexEnd{display:flex;justify-content:flex-end}.logo{height:50px}.responsiveNavbar{display:none;align-items:center;height:51px}.line{line-height:12px}.pageBrand{font-size:18px;padding:0 10px;margin-bottom:-4px;display:flex;justify-content:center}.pageMenu{margin-top:0}.alingCenterline{display:flex;align-items:center}.dropdownIcon{top:1px;margin-top:7px;font-weight:700}.active{color:var(--white-color);background-color:var(--primary-color)}.matmenuIcon{display:flex;align-items:center;color:var(--grey-color)}.padding{padding-left:10px}.bigPadding{padding-left:40px}.black{color:var(--black-color)}.responsiveLogo{margin-top:-5px}"]}]}],"members":{"openDrawer":[{"__symbolic":"property","decorators":[{"__symbolic":"call","expression":{"__symbolic":"reference","module":"@angular/core","name":"Output","line":8,"character":3}}]}],"currentUser":[{"__symbolic":"property","decorators":[{"__symbolic":"call","expression":{"__symbolic":"reference","module":"@angular/core","name":"Input","line":9,"character":3}}]}],"logo":[{"__symbolic":"property","decorators":[{"__symbolic":"call","expression":{"__symbolic":"reference","module":"@angular/core","name":"Input","line":10,"character":3}}]}],"Logout":[{"__symbolic":"property","decorators":[{"__symbolic":"call","expression":{"__symbolic":"reference","module":"@angular/core","name":"Output","line":11,"character":3}}]}],"__ctor__":[{"__symbolic":"constructor"}],"ngOnInit":[{"__symbolic":"method"}],"onSignout":[{"__symbolic":"method"}],"openSideNav":[{"__symbolic":"method"}]}},"SidenavComponent":{"__symbolic":"class","decorators":[{"__symbolic":"call","expression":{"__symbolic":"reference","module":"@angular/core","name":"Component","line":1,"character":1},"arguments":[{"selector":"app-sidenav","template":"  <div class=\"sideNavheading\" routerLink=\"../programs\"  matTooltip=\"{{'message.goToProgramDashboard' | translate}}\" *ngIf=\"programsShow\">\n    <i class=\"material-icons\">\n      keyboard_arrow_left\n    </i> {{ 'headings.programs' | translate }}\n  </div>\n    <!-- <div routerLink = \"{{option.anchorLink}}\"  [routerLinkActiveOptions]=\"{exact:true}\" routerLinkActive=\"active\"*ngFor=\"let option of link?.options\"  class=\"subHeading\"> -->\n    <!-- <div [routerLink]=\"['assessments/:programId/:assessmentId/'+option.link?.anchorLink,option.link.programId,option.link.assessmentId ]\" routerLinkActive=\"active\" *ngFor=\"let option of link?.options\"  class=\"subHeading\"> -->\n        <!-- <div [routerLink]=\"[option.link.anchorLink ]\"  [queryParamsHandling]=\"preserve\" [queryParams]=\"{ programId : option.link.programId , assessmentId : option.link.assessmentId}\" routerLinkActive=\"active\" *ngFor=\"let option of link?.options\"  class=\"subHeading\"> -->\n\n\n\n    <div [routerLink]=\"[option.anchorLink ]\"  routerLinkActive=\"active\" *ngFor=\"let option of link?.options\"  class=\"subHeading\">\n        <span class=\"sideNavSubheading\"> \n            {{ option.value | translate }}\n          </span>\n      </div>\n   ","styles":[".sideNavSubheading{font-size:15px;padding:10px 23px;height:40px;display:flex;cursor:pointer}.subHeading{color:var(--grey-color)}.sideNavheading{height:40px;display:flex;align-items:center;padding:0 0 0 5px;cursor:pointer}.active,.sideNavheading:hover,.subHeading:hover{color:var(--white-color);background-color:var(--primary-color)}"]}]}],"members":{"link":[{"__symbolic":"property","decorators":[{"__symbolic":"call","expression":{"__symbolic":"reference","module":"@angular/core","name":"Input","line":7,"character":3}}]}],"programsShow":[{"__symbolic":"property","decorators":[{"__symbolic":"call","expression":{"__symbolic":"reference","module":"@angular/core","name":"Input","line":8,"character":3}}]}],"__ctor__":[{"__symbolic":"constructor"}],"ngOnInit":[{"__symbolic":"method"}]}}},"origins":{"CoreModule":"./lib/core.module","CamelCasePipe":"./lib/pipes/camelcase-pipe/camelcase.pipe","NoValuePipe":"./lib/pipes/no-value-pipe/no-value.pipe","TranslatePipe":"./lib/pipes/translate-pipe/translate.pipe","ApiService":"./lib/services/api-service/api.service","ApiInterceptor":"./lib/services/interceptor-service/interceptor.service","TranslateService":"./lib/services/translate-service/translate.service","UtilityService":"./lib/services/utility-service/utility.service","NavbarComponent":"./lib/components/navbar/navbar.component","ProgramSidenavComponent":"./lib/components/program-sidenav/program-sidenav.component","ResponsiveNavbarComponent":"./lib/components/responsive-navbar/responsive-navbar.component","SidenavComponent":"./lib/components/sidenav/sidenav.component"},"importAs":"shikshalokamcoremodule"}